tarte_ai/__init__.py
tarte_ai/gbdt_bagging_es.py
tarte_ai/tarte_boost_tabpfn.py
tarte_ai/tarte_boost_xgb.py
tarte_ai/tarte_estimator_nn.py
tarte_ai/tarte_finetune_estimator.py
tarte_ai/tarte_gridsearch.py
tarte_ai/tarte_model.py
tarte_ai/tarte_preprocess_kg.py
tarte_ai/tarte_preprocess_table.py
tarte_ai/tarte_pretrain.py
tarte_ai/tarte_utils.py
tarte_ai-0.0.6.dist-info/licenses/LICENSE.txt
tarte_ai-0.0.6.dist-info/METADATA
tarte_ai-0.0.6.dist-info/WHEEL
tarte_ai-0.0.6.dist-info/top_level.txt
tarte_ai-0.0.6.dist-info/RECORD
