Metadata-Version: 2.4
Name: tarte-ai
Version: 0.0.6
Summary: TARTE-AI: Transformer Augmented Representation of Tabular Entries
Author: Myung Jun Kim, Felix Lefebvre, Gaetan Brison, Alexandre Perez-Lebel, Gael Varoquaux
License: BSD-3-Clause license
Project-URL: Homepage, https://github.com/soda-inria/tarte-ai
Project-URL: Repository, https://github.com/soda-inria/tarte-ai
Project-URL: Issues, https://github.com/soda-inria/tarte-ai/issues
Project-URL: Documentation, https://github.com/soda-inria/tarte-ai#readme
Keywords: tarte-ai
Classifier: Development Status :: 2 - Pre-Alpha
Classifier: Intended Audience :: Developers
Classifier: License :: OSI Approved :: BSD License
Classifier: Environment :: Console
Classifier: Operating System :: OS Independent
Classifier: Operating System :: POSIX :: Linux
Classifier: Operating System :: MacOS
Classifier: Operating System :: POSIX
Classifier: Operating System :: Microsoft :: Windows
Classifier: Natural Language :: English
Classifier: Programming Language :: Python :: 3.12
Classifier: Programming Language :: Python :: 3.13
Classifier: Programming Language :: Python :: 3.14
Requires-Python: >=3.11.00
License-File: LICENSE.txt
Requires-Dist: numpy
Requires-Dist: pandas
Requires-Dist: scipy
Requires-Dist: scikit-learn
Requires-Dist: torch
Requires-Dist: torcheval
Requires-Dist: fasttext
Requires-Dist: huggingface_hub
Requires-Dist: catboost
Requires-Dist: tabpfn
Requires-Dist: xgboost
Requires-Dist: skrub
Requires-Dist: pyarrow
Requires-Dist: fastparquet
Provides-Extra: test
Requires-Dist: pytest; extra == "test"
Requires-Dist: coverage; extra == "test"
Dynamic: license-file
